async_universalis/__init__.py
async_universalis/_enums.py
async_universalis/_types.py
async_universalis/errors.py
async_universalis/py.typed
async_universalis-3.0.1.dev0.dist-info/licenses/LICENSE
async_universalis-3.0.1.dev0.dist-info/METADATA
async_universalis-3.0.1.dev0.dist-info/WHEEL
async_universalis-3.0.1.dev0.dist-info/top_level.txt
async_universalis-3.0.1.dev0.dist-info/RECORD
