Metadata-Version: 2.4
Name: async_universalis
Version: 3.0.1.dev0
Summary: A bare-bones wrapper package to utilitize Universalis API in python.
Author-email: k8thekat <Cadwalladerkatelynn@gmail.com>
License:                     GNU GENERAL PUBLIC LICENSE
Project-URL: GitHub, https://github.com/k8thekat/UniversalisAPI_wrapper
Keywords: ffxiv,datamining,universalis,api
Classifier: Development Status :: 5 - Production/Stable
Classifier: Intended Audience :: Developers
Classifier: License :: OSI Approved :: GNU General Public License v3 or later (GPLv3+)
Classifier: Operating System :: OS Independent
Classifier: Programming Language :: Python :: 3.12
Classifier: Framework :: AsyncIO
Classifier: Topic :: Internet
Classifier: Topic :: Software Development :: Libraries
Classifier: Topic :: Software Development :: Libraries :: Python Modules
Classifier: Topic :: Utilities
Classifier: Typing :: Typed
Requires-Python: >=3.12.0
License-File: LICENSE
Requires-Dist: aiohttp>=3.12.13
Dynamic: license-file
